django_wilayah_indonesia-0.2.0.dist-info/licenses/LICENSE
wilayah_indonesia/__init__.py
wilayah_indonesia/admin.py
wilayah_indonesia/apps.py
wilayah_indonesia/forms.py
wilayah_indonesia/models.py
wilayah_indonesia/tests.py
wilayah_indonesia/urls.py
wilayah_indonesia/views.py
wilayah_indonesia/__pycache__/__init__.cpython-310.pyc
wilayah_indonesia/__pycache__/__init__.cpython-311.pyc
wilayah_indonesia/__pycache__/admin.cpython-310.pyc
wilayah_indonesia/__pycache__/admin.cpython-311.pyc
wilayah_indonesia/__pycache__/apps.cpython-310.pyc
wilayah_indonesia/__pycache__/apps.cpython-311.pyc
wilayah_indonesia/__pycache__/forms.cpython-311.pyc
wilayah_indonesia/__pycache__/models.cpython-310.pyc
wilayah_indonesia/__pycache__/models.cpython-311.pyc
wilayah_indonesia/__pycache__/urls.cpython-311.pyc
wilayah_indonesia/__pycache__/views.cpython-311.pyc
wilayah_indonesia/csv/__init__.py
wilayah_indonesia/csv/base.csv
wilayah_indonesia/csv/districts.csv
wilayah_indonesia/csv/provinces.csv
wilayah_indonesia/csv/regencies.csv
wilayah_indonesia/csv/villages.csv
wilayah_indonesia/csv/__pycache__/__init__.cpython-311.pyc
wilayah_indonesia/management/__init__.py
wilayah_indonesia/management/__pycache__/__init__.cpython-311.pyc
wilayah_indonesia/management/commands/__init__.py
wilayah_indonesia/management/commands/cleanup_old_wilayah.py
wilayah_indonesia/management/commands/import_base_csv.py
wilayah_indonesia/management/commands/migrate_wilayah_relations.py
wilayah_indonesia/management/commands/region_seeding.py
wilayah_indonesia/management/commands/__pycache__/__init__.cpython-311.pyc
wilayah_indonesia/management/commands/__pycache__/cleanup_old_wilayah.cpython-311.pyc
wilayah_indonesia/management/commands/__pycache__/import_base_csv.cpython-311.pyc
wilayah_indonesia/management/commands/__pycache__/migrate_wilayah_relations.cpython-311.pyc
wilayah_indonesia/management/commands/__pycache__/region_seeding.cpython-310.pyc
wilayah_indonesia/management/commands/__pycache__/region_seeding.cpython-311.pyc
django_wilayah_indonesia-0.2.0.dist-info/METADATA
django_wilayah_indonesia-0.2.0.dist-info/WHEEL
django_wilayah_indonesia-0.2.0.dist-info/top_level.txt
django_wilayah_indonesia-0.2.0.dist-info/RECORD
